rcc/__init__.py
rcc/binpack.py
rcc/client.py
rcc/connection.py
rcc/hash_slot.py
rcc/multiplexed_client.py
rcc/plot.py
rcc/pool.py
rcc/response.py
rcc/subscriber.py
rcc/version.py
rcc/cluster/__init__.py
rcc/cluster/create.py
rcc/cluster/forget.py
rcc/cluster/info.py
rcc/cluster/init_cluster.py
rcc/cluster/keyspace_analyzer.py
rcc/cluster/reshard.py
rcc/commands/__init__.py
rcc/commands/cluster.py
rcc/commands/generic.py
rcc/commands/pubsub.py
rcc/data/example-weights.csv
rcc/data/weights.json
rcc/runner/__init__.py
rcc/runner/cli.py
rcc/runner/cluster_check.py
rcc/runner/cluster_forget.py
rcc/runner/cluster_init.py
rcc/runner/cluster_move_slots.py
rcc/runner/cluster_nodes.py
rcc/runner/cluster_slots.py
rcc/runner/endpoints.py
rcc/runner/keyspace.py
rcc/runner/make_cluster.py
rcc/runner/migrate.py
rcc/runner/publish.py
rcc/runner/reshard.py
rcc/runner/sub.py
rcc/runner/subscribe.py
rcc/runner/top.py
rcc/vendor/__init__.py
rcc/vendor/bar_chart.py
rcc-0.9.154.dist-info/LICENSE.txt
rcc-0.9.154.dist-info/METADATA
rcc-0.9.154.dist-info/WHEEL
rcc-0.9.154.dist-info/entry_points.txt
rcc-0.9.154.dist-info/top_level.txt
rcc-0.9.154.dist-info/RECORD
