Metadata-Version: 2.1
Name: rcc
Version: 0.9.154
Summary: A simple asyncio redis client with cluster support and a resharding cli tool.
Home-page: https://github.com/machinezone/rcc
Author: Benjamin Sergeant
Author-email: bsergean@gmail.com
License: BSD 3
Platform: UNKNOWN
Classifier: Development Status :: 3 - Alpha
Classifier: Environment :: Web Environment
Classifier: Intended Audience :: Developers
Classifier: License :: OSI Approved :: BSD License
Classifier: Operating System :: OS Independent
Classifier: Programming Language :: Python
Classifier: Programming Language :: Python :: 3
Classifier: Programming Language :: Python :: 3.6
Classifier: Programming Language :: Python :: 3.7
Classifier: Programming Language :: Python :: 3.8
Classifier: Programming Language :: Python :: 3.9
Requires-Dist: click (>=7.0)
Requires-Dist: coloredlogs (>=10.0)
Requires-Dist: hiredis (>=1.0.1)
Requires-Dist: tabulate (>=0.8.5)
Provides-Extra: dev
Requires-Dist: wheel ; extra == 'dev'
Requires-Dist: isort ; extra == 'dev'
Requires-Dist: twine ; extra == 'dev'
Requires-Dist: black ; extra == 'dev'
Requires-Dist: pre-commit ; extra == 'dev'
